README
bib2bbl.py
setup.cfg
setup.py
bib2bbl.egg-info/PKG-INFO
bib2bbl.egg-info/SOURCES.txt
bib2bbl.egg-info/dependency_links.txt
bib2bbl.egg-info/top_level.txt
scripts/bib2bbl