Metadata-Version: 1.0
Name: bib2bbl
Version: v3
Summary: bibtex to bib items converter a utility for latex documents
Home-page: http://www.jaist.ac.jp/~s1010205/
Author: KATHURIA Pulkit
Author-email: kevincobain2000@gmail.com
License: BSD
Platform: UNKNOWN
Classifier: Development Status :: 6 - Mature
Classifier: Topic :: Utilities
